pydenticore/__init__.py
pydenticore/authentication/__init__.py
pydenticore/authentication/_base.py
pydenticore/authentication/interfaces/__init__.py
pydenticore/authorization/__init__.py
pydenticore/authorization/_base.py
pydenticore/authorization/interfaces/__init__.py
pydenticore/dataprotector.py
pydenticore/exc.py
pydenticore/hashers/__init__.py
pydenticore/hashers/password_hasher.py
pydenticore/http/__init__.py
pydenticore/http/context.py
pydenticore/identity_constants.py
pydenticore/identity_error.py
pydenticore/identity_error_describer.py
pydenticore/identity_options.py
pydenticore/identity_result.py
pydenticore/interfaces/__init__.py
pydenticore/interfaces/logger.py
pydenticore/interfaces/lookup_normalizer.py
pydenticore/interfaces/password_hasher.py
pydenticore/interfaces/password_validator.py
pydenticore/interfaces/protector.py
pydenticore/interfaces/role_validator.py
pydenticore/interfaces/stores/__init__.py
pydenticore/interfaces/stores/role_store.py
pydenticore/interfaces/stores/user_store.py
pydenticore/interfaces/token_provider.py
pydenticore/interfaces/user_claims_principal_factory.py
pydenticore/interfaces/user_confirmation.py
pydenticore/interfaces/user_validator.py
pydenticore/loggers.py
pydenticore/lookup_normalizer.py
pydenticore/resources/__init__.py
pydenticore/resources/_error_messages.py
pydenticore/role_manager.py
pydenticore/security/__init__.py
pydenticore/security/claims/__init__.py
pydenticore/security/claims/claim_types.py
pydenticore/security/claims/claims.py
pydenticore/security/claims/serializer.py
pydenticore/signin_manager.py
pydenticore/token_providers/__init__.py
pydenticore/token_providers/rfc6238service.py
pydenticore/token_providers/token_provider.py
pydenticore/types/__init__.py
pydenticore/types/decorators.py
pydenticore/user_claims_principal_factory.py
pydenticore/user_confirmation.py
pydenticore/user_login_info.py
pydenticore/user_manager.py
pydenticore/utils/__init__.py
pydenticore/validators/__init__.py
pydenticore-0.1.7.dist-info/METADATA
pydenticore-0.1.7.dist-info/WHEEL
pydenticore-0.1.7.dist-info/RECORD
